bjgrader/__init__.py
bjgrader/__main__.py
bjgrader/bjgrader.py
bjgrader-0.0.5.dist-info/LICENSE
bjgrader-0.0.5.dist-info/METADATA
bjgrader-0.0.5.dist-info/WHEEL
bjgrader-0.0.5.dist-info/top_level.txt
bjgrader-0.0.5.dist-info/RECORD
